MANIFEST.in
README.md
setup.py
baidu_trans/__init__.py
baidu_trans/baidu_api.py
baidu_trans/setting.py
baidu_trans.egg-info/PKG-INFO
baidu_trans.egg-info/SOURCES.txt
baidu_trans.egg-info/dependency_links.txt
baidu_trans.egg-info/top_level.txt