Metadata-Version: 2.1
Name: baidu_trans
Version: 0.1.3
Summary: Free baidu Translate API for Python. Translates totally free of charge.
Home-page: https://github.com/Scoefield/PythonLearning
Author: scoefield
Author-email: scoefielddeng@gmail.com
License: MIT
Keywords: baidu translate translator
Platform: UNKNOWN
Classifier: Development Status :: 5 - Production/Stable
Classifier: Intended Audience :: Education
Classifier: Intended Audience :: End Users/Desktop
Classifier: License :: Freeware
Classifier: Operating System :: POSIX
Classifier: Operating System :: Microsoft :: Windows
Classifier: Operating System :: MacOS :: MacOS X
Classifier: Topic :: Education
Classifier: Programming Language :: Python :: 3.4
Classifier: Programming Language :: Python :: 3.5
Classifier: Programming Language :: Python :: 3.6
